.gitignore
.pre-commit-config.yaml
CMakeLists.txt
LICENSE
README.md
example.ipynb
pyproject.toml
setup.py
.github/workflows/pytest_linux.yml
.github/workflows/pytest_windows.yml
.github/workflows/release.yml
cmake/CPM.cmake
src/CMakeLists.txt
src/cgshop2025_pyutils/CMakeLists.txt
src/cgshop2025_pyutils/__init__.py
src/cgshop2025_pyutils.egg-info/PKG-INFO
src/cgshop2025_pyutils.egg-info/SOURCES.txt
src/cgshop2025_pyutils.egg-info/dependency_links.txt
src/cgshop2025_pyutils.egg-info/requires.txt
src/cgshop2025_pyutils.egg-info/top_level.txt
src/cgshop2025_pyutils/data_schemas/__init__.py
src/cgshop2025_pyutils/data_schemas/instance.py
src/cgshop2025_pyutils/data_schemas/solution.py
src/cgshop2025_pyutils/generators/__init__.py
src/cgshop2025_pyutils/generators/_random_points.py
src/cgshop2025_pyutils/generators/orthogonal.py
src/cgshop2025_pyutils/generators/point_set.py
src/cgshop2025_pyutils/generators/simple_polygons.py
src/cgshop2025_pyutils/generators/verify_instance.py
src/cgshop2025_pyutils/geometry/CMakeLists.txt
src/cgshop2025_pyutils/geometry/__init__.py
src/cgshop2025_pyutils/geometry/_bindings.cpp
src/cgshop2025_pyutils/instance_database/__init__.py
src/cgshop2025_pyutils/instance_database/instance_base_database.py
src/cgshop2025_pyutils/instance_database/instance_database.py
src/cgshop2025_pyutils/instance_database/instance_file_database.py
src/cgshop2025_pyutils/instance_database/instance_zip_database.py
src/cgshop2025_pyutils/io/__init__.py
src/cgshop2025_pyutils/naive_algorithm/__init__.py
src/cgshop2025_pyutils/naive_algorithm/delaunay_based.py
src/cgshop2025_pyutils/verifier/__init__.py
src/cgshop2025_pyutils/verifier/verifier.py
src/cgshop2025_pyutils/visualization/__init__.py
src/cgshop2025_pyutils/visualization/instance.py
src/cgshop2025_pyutils/zip/__init__.py
src/cgshop2025_pyutils/zip/zip_processor.py
src/cgshop2025_pyutils/zip/zip_reader_errors.py
src/cgshop2025_pyutils/zip/zip_writer.py
tests/test_geometry.py
tests/test_verify.py